{
  "project_info": {
    "project_number": "317938665213",
    "project_id": "todolist-94119",
    "storage_bucket": "todolist-94119.firebasestorage.app"
  },
  "client": [
    {
      "client_info": {
        "mobilesdk_app_id": "1:317938665213:android:e7b93cd329aa6289642094",
        "android_client_info": {
          "package_name": "com.example.toDoList"
        }
      },
      "oauth_client": [],
      "api_key": [
        {
          "current_key": "AIzaSyDSzK0dIzCogi3y9gVbBoriKwoz_wckaow"
        }
      ],
      "services": {
        "appinvite_service": {
          "other_platform_oauth_client": []
        }
      }
    }
  ],
  "configuration_version": "1"
}